pyaemet/__init__.py
pyaemet/aemet_request.py
pyaemet/climatology.py
pyaemet/static/__init__.py
pyaemet/static/sites/data.csv
pyaemet/static/sites/metadata.json
pyaemet/types_classes/__init__.py
pyaemet/types_classes/observations.py
pyaemet/types_classes/sites.py
pyaemet/utilities/__init__.py
pyaemet/utilities/coordinates.py
pyaemet/utilities/curation.py
pyaemet/utilities/dictionaries.py
pyaemet-1.1.1.dist-info/METADATA
pyaemet-1.1.1.dist-info/WHEEL
pyaemet-1.1.1.dist-info/licenses/LICENSE
pyaemet-1.1.1.dist-info/RECORD
