Metadata-Version: 2.4
Name: pyaemet
Version: 1.1.1
Summary: Python module to interact with the AEMET API to download meteorological data
Project-URL: Homepage, https://github.com/jaimedgp/pyAEMET
Project-URL: Repository, https://github.com/jaimedgp/pyAEMET
Project-URL: Bug Tracker, https://github.com/jaimedgp/pyAEMET/issues
Author-email: Jaimedgp <jaime.diez.gp@gmail.com>
Maintainer-email: CarmenGBM <carmen.garcia.be96@gmail.com>
License: GPL-3.0-or-later
License-File: LICENSE
Keywords: AEMET,AEMET OpenData,API,Meteorology
Classifier: Operating System :: OS Independent
Classifier: Programming Language :: Python :: 3
Requires-Python: >=3.10
Requires-Dist: folium>=0.11.0
Requires-Dist: geocoder>=1.38.0
Requires-Dist: matplotlib>=3.2.2
Requires-Dist: numpy>=1.19.0
Requires-Dist: pandas>=1.1.0
Requires-Dist: requests>=2.24.0
Requires-Dist: setuptools>=75.8.0
Requires-Dist: tqdm>=4.46.1
